LICENSE
README.rst
setup.cfg
setup.py
binance/__init__.py
binance/client.py
binance/depthcache.py
binance/enums.py
binance/exceptions.py
binance/helpers.py
binance/streams.py
binance/threaded_stream.py
python_binance_fixed.egg-info/PKG-INFO
python_binance_fixed.egg-info/SOURCES.txt
python_binance_fixed.egg-info/dependency_links.txt
python_binance_fixed.egg-info/requires.txt
python_binance_fixed.egg-info/top_level.txt